j2subst/__init__.py
j2subst/__main__.py
j2subst/cli.py
j2subst/cli_help.py
j2subst/defaults.py
j2subst/dumpfmt.py
j2subst/functions.py
j2subst/j2subst.py
j2subst/dist/requirements.txt
j2subst/tests/example.j2
j2subst-0.0.4.dist-info/licenses/LICENSE
j2subst-0.0.4.dist-info/METADATA
j2subst-0.0.4.dist-info/WHEEL
j2subst-0.0.4.dist-info/entry_points.txt
j2subst-0.0.4.dist-info/top_level.txt
j2subst-0.0.4.dist-info/RECORD
