Metadata-Version: 2.4
Name: j2subst
Version: 0.0.4
Summary: Jinja2 template substitution tool
Author-email: Konstantin Demin <rockdrilla@gmail.com>
License-Expression: Apache-2.0
Project-URL: Homepage, https://github.com/rockdrilla/j2subst
Project-URL: Bug Reports, https://github.com/rockdrilla/j2subst/issues
Project-URL: Source Code, https://github.com/rockdrilla/j2subst
Project-URL: Docker Image, https://hub.docker.com/r/rockdrilla/j2subst/tags
Keywords: automation,ci-cd,configuration,deployment,environment,infrastructure,jinja2,json,substitution,templates,toml,yaml
Classifier: Development Status :: 4 - Beta
Classifier: Intended Audience :: Developers
Classifier: Intended Audience :: Information Technology
Classifier: Intended Audience :: System Administrators
Classifier: Operating System :: POSIX
Classifier: Programming Language :: Python :: 3
Classifier: Programming Language :: Python :: 3.11
Classifier: Programming Language :: Python :: 3.12
Classifier: Programming Language :: Python :: 3.13
Classifier: Programming Language :: Python :: 3.14
Classifier: Topic :: Software Development :: Code Generators
Classifier: Topic :: Software Development :: Libraries :: Python Modules
Classifier: Topic :: Text Processing :: Markup
Classifier: Topic :: Utilities
Requires-Python: >=3.11
License-File: LICENSE
Requires-Dist: click<8.4.0,>=8.3.0
Requires-Dist: jinja2<3.2.0,>=3.1.6
Requires-Dist: natsort<8.5.0,>=8.4.0
Requires-Dist: pyyaml<6.1.0,>=6.0.3
Dynamic: license-file
